uhd_wrapper/__init__.py
uhd_wrapper/versioning.py
uhd_wrapper/rpc_server/__init__.py
uhd_wrapper/rpc_server/reconfigurable_usrp.py
uhd_wrapper/rpc_server/rpc_server.py
uhd_wrapper/utils/__init__.py
uhd_wrapper/utils/config.py
uhd_wrapper/utils/serialization.py
usrp_client/__init__.py
usrp_client/errors.py
usrp_client/rpc_client.py
usrp_client/sanity.py
usrp_client/system.py
usrp_uhd_client-1.7.3.dist-info/LICENSE
usrp_uhd_client-1.7.3.dist-info/METADATA
usrp_uhd_client-1.7.3.dist-info/WHEEL
usrp_uhd_client-1.7.3.dist-info/top_level.txt
usrp_uhd_client-1.7.3.dist-info/RECORD
