Metadata-Version: 2.1
Name: usrp-uhd-client
Version: 1.7.3
Summary: Universal Software Defined Radio Hardware Driver Remote Client
Home-page: https://github.com/Barkhausen-Institut/usrp_uhd_wrapper
Author: Maximilian Matthé
Author-email: maximilian.matthe@barkhauseninstitut.org
Project-URL: Documentation, https://barkhausen-institut.github.io/usrp_uhd_wrapper
Project-URL: Barkhausen Institute, https://www.barkhauseninstitut.org
Project-URL: Bug Tracker, https://github.com/Barkhausen-Institut/usrp_uhd_wrapper/issues
Classifier: Programming Language :: Python :: 3.9
Classifier: Programming Language :: Python :: 3.10
Classifier: Programming Language :: Python :: 3.11
Classifier: License :: OSI Approved :: GNU Affero General Public License v3
Classifier: Operating System :: OS Independent
Classifier: Development Status :: 2 - Pre-Alpha
Classifier: Natural Language :: English
Classifier: Topic :: Scientific/Engineering
Requires-Python: >=3.9
License-File: LICENSE
Requires-Dist: zerorpc ~=0.6.3
Requires-Dist: pyzmq ~=25.1.1
Requires-Dist: numpy >=1.23.5
Requires-Dist: matplotlib >=3.6.2
Requires-Dist: dataclasses-json ~=0.5.7
